wordvariations/README.MD
wordvariations/__init__.py
wordvariations/requirements.txt
wordvariations/thirdparty.json
wordvariations-0.10.dist-info/LICENSE.rst
wordvariations-0.10.dist-info/METADATA
wordvariations-0.10.dist-info/WHEEL
wordvariations-0.10.dist-info/top_level.txt
wordvariations-0.10.dist-info/RECORD
