Metadata-Version: 2.1
Name: wordvariations
Version: 0.10
Summary: Generates possible typing errors from a given string (neighboring keys and switch letters)
Home-page: https://github.com/hansalemaos/wordvariations
Author: Johannes Fischer
Author-email: aulasparticularesdealemaosp@gmail.com
License: MIT
Keywords: string,typing,errors
Classifier: Development Status :: 4 - Beta
Classifier: Programming Language :: Python :: 3 :: Only
Classifier: Programming Language :: Python :: 3.10
Classifier: Topic :: Software Development :: Libraries :: Python Modules
Classifier: Topic :: Utilities
License-File: LICENSE.rst
Requires-Dist: ordered-set
Requires-Dist: pandas
Requires-Dist: surroundingkeys
